nts/__init__.py
nts/__main__.py
nts/cli.py
nts/downloader.py
nts_everdrone-1.3.8.dist-info/METADATA
nts_everdrone-1.3.8.dist-info/WHEEL
nts_everdrone-1.3.8.dist-info/entry_points.txt
nts_everdrone-1.3.8.dist-info/top_level.txt
nts_everdrone-1.3.8.dist-info/RECORD
