Metadata-Version: 2.4
Name: nts-everdrone
Version: 1.3.8
Summary: NTS Radio downloader tool
Home-page: https://github.com/everdrone/nts
Author: Giorgio Tropiano
Author-email: giorgiotropiano@gmail.com
License: MIT
Classifier: Programming Language :: Python :: 3
Classifier: License :: OSI Approved :: MIT License
Classifier: Operating System :: OS Independent
Requires-Python: >=3.7.5
Requires-Dist: yt-dlp==2024.7.25
Requires-Dist: beautifulsoup4==4.9.3
Requires-Dist: mutagen==1.45.1
Requires-Dist: requests==2.32.4
Requires-Dist: cssutils==2.7.1
Requires-Dist: ffmpeg-python==0.2.0
Requires-Dist: music-tag==0.4.3
Requires-Dist: pillow==10.4.0
Dynamic: author
Dynamic: author-email
Dynamic: classifier
Dynamic: description
Dynamic: description-content-type
Dynamic: home-page
Dynamic: license
Dynamic: requires-dist
Dynamic: requires-python
Dynamic: summary
